cqlsh_expansion/__init__.py
cqlsh_expansion/__main__.py
cqlsh_expansion/__main_expansion__.py
cqlsh_expansion/cqlsh.py
cqlsh_expansion/cqlsh_expansion.py
cqlsh_expansion/cqlshrc_template
cqlsh_expansion/describe_usage.py
cqlsh_expansion/post_install.py
cqlsh_expansion/sf-class2-root.crt
cqlshlib/__init__.py
cqlshlib/authproviderhandling.py
cqlshlib/copyutil.py
cqlshlib/cql3handling.py
cqlshlib/cqlhandling.py
cqlshlib/cqlshhandling.py
cqlshlib/describe_function3x.py
cqlshlib/displaying.py
cqlshlib/formatting.py
cqlshlib/helptopics.py
cqlshlib/pylexotron.py
cqlshlib/saferscanner.py
cqlshlib/sslhandling.py
cqlshlib/tracing.py
cqlshlib/util.py
cqlshlib/wcwidth.py
cqlsh_expansion-0.9.6.dist-info/LICENSE.txt
cqlsh_expansion-0.9.6.dist-info/METADATA
cqlsh_expansion-0.9.6.dist-info/THIRD-PARTY-LICENSES.txt
cqlsh_expansion-0.9.6.dist-info/WHEEL
cqlsh_expansion-0.9.6.dist-info/entry_points.txt
cqlsh_expansion-0.9.6.dist-info/top_level.txt
cqlsh_expansion-0.9.6.dist-info/RECORD
