Metadata-Version: 2.1
Name: cqlsh-expansion
Version: 0.9.6
Summary: The cqlsh-expansion utility extends native cqlsh functionality to include cloud native capabilities
Home-page: https://github.com/aws-samples/amazon-keyspaces-toolkit/tree/master/cqlsh-expansion
Author: Michael Raney, Sri Rathan Rangisetti
Keywords: cql,cqlsh,cqlsh-expansion,aws,keyspaces,cassandra,sigv4
Classifier: Development Status :: 5 - Production/Stable
Classifier: Intended Audience :: Developers
Classifier: License :: OSI Approved :: Apache Software License
Classifier: Operating System :: OS Independent
Classifier: Programming Language :: Python
Classifier: Programming Language :: Python :: 3.4
Classifier: Programming Language :: Python :: 3.5
Classifier: Programming Language :: Python :: 3.6
Classifier: Programming Language :: Python :: 3.7
Classifier: Programming Language :: Python :: Implementation :: CPython
Classifier: Programming Language :: Python :: Implementation :: PyPy
Classifier: Topic :: Software Development :: Libraries :: Python Modules
Requires-Python: >=3.6
License-File: THIRD-PARTY-LICENSES.txt
License-File: LICENSE.txt
Requires-Dist: six >=1.12.0
Requires-Dist: cassandra-driver
Requires-Dist: boto3
Requires-Dist: cassandra-sigv4 >=4.0.2
